nonebot_plugin_xiuxian/__init__.py
nonebot_plugin_xiuxian/cd_manager.py
nonebot_plugin_xiuxian/command.py
nonebot_plugin_xiuxian/data_source.py
nonebot_plugin_xiuxian/help.py
nonebot_plugin_xiuxian/item_json.py
nonebot_plugin_xiuxian/player_fight.py
nonebot_plugin_xiuxian/read_buff.py
nonebot_plugin_xiuxian/tests.py
nonebot_plugin_xiuxian/utils.py
nonebot_plugin_xiuxian/xiuxian2_handle.py
nonebot_plugin_xiuxian/xiuxian_config.py
nonebot_plugin_xiuxian/xiuxian_opertion.py
nonebot_plugin_xiuxian/xiuxian_back/__init__.py
nonebot_plugin_xiuxian/xiuxian_back/back_util.py
nonebot_plugin_xiuxian/xiuxian_back/backconfig.py
nonebot_plugin_xiuxian/xiuxian_bank/__init__.py
nonebot_plugin_xiuxian/xiuxian_bank/bankconfig.py
nonebot_plugin_xiuxian/xiuxian_boss/__init__.py
nonebot_plugin_xiuxian/xiuxian_boss/boss_handle.py
nonebot_plugin_xiuxian/xiuxian_boss/bossconfig.py
nonebot_plugin_xiuxian/xiuxian_boss/makeboss.py
nonebot_plugin_xiuxian/xiuxian_buff/__init__.py
nonebot_plugin_xiuxian/xiuxian_info/__init__.py
nonebot_plugin_xiuxian/xiuxian_info/download.py
nonebot_plugin_xiuxian/xiuxian_info/draw_user_info.py
nonebot_plugin_xiuxian/xiuxian_info/font.ttf
nonebot_plugin_xiuxian/xiuxian_info/infoconfig.py
nonebot_plugin_xiuxian/xiuxian_info/send_image_tool.py
nonebot_plugin_xiuxian/xiuxian_info/texture2d/back.png
nonebot_plugin_xiuxian/xiuxian_info/texture2d/line2.png
nonebot_plugin_xiuxian/xiuxian_info/texture2d/line3.png
nonebot_plugin_xiuxian/xiuxian_info/texture2d/line4.png
nonebot_plugin_xiuxian/xiuxian_info/texture2d/user_state.png
nonebot_plugin_xiuxian/xiuxian_mixelixir/__init__.py
nonebot_plugin_xiuxian/xiuxian_mixelixir/mix_elixir_config.py
nonebot_plugin_xiuxian/xiuxian_mixelixir/mixelixirutil.py
nonebot_plugin_xiuxian/xiuxian_rift/__init__.py
nonebot_plugin_xiuxian/xiuxian_rift/jsondata.py
nonebot_plugin_xiuxian/xiuxian_rift/riftconfig.py
nonebot_plugin_xiuxian/xiuxian_rift/riftmake.py
nonebot_plugin_xiuxian/xiuxian_sect/__init__.py
nonebot_plugin_xiuxian-0.4.33.dist-info/LICENSE.txt
nonebot_plugin_xiuxian-0.4.33.dist-info/METADATA
nonebot_plugin_xiuxian-0.4.33.dist-info/WHEEL
nonebot_plugin_xiuxian-0.4.33.dist-info/top_level.txt
nonebot_plugin_xiuxian-0.4.33.dist-info/RECORD
